pygamer/__init__.py
pygamer/pygamer.cpython-37m-darwin.so
pygamer-2.0.2.data/data/include/gamer/MarchingCube.h
pygamer-2.0.2.data/data/include/gamer/PDBReader.h
pygamer-2.0.2.data/data/include/gamer/SurfaceMesh.h
pygamer-2.0.2.data/data/include/gamer/TetMesh.h
pygamer-2.0.2.data/data/include/gamer/Vertex.h
pygamer-2.0.2.data/data/include/gamer/gamer.h
pygamer-2.0.2.data/data/include/gamer/stringutil.h
pygamer-2.0.2.data/data/include/gamer/tensor.h
pygamer-2.0.2.data/data/include/gamer/version.h
pygamer-2.0.2.data/data/lib/libgamer.a
pygamer-2.0.2.data/data/lib/libgamer.dylib
pygamer-2.0.2.dist-info/COPYING.md
pygamer-2.0.2.dist-info/METADATA
pygamer-2.0.2.dist-info/WHEEL
pygamer-2.0.2.dist-info/top_level.txt
pygamer-2.0.2.dist-info/RECORD
