Metadata-Version: 2.1
Name: pygamer
Version: 2.0.2
Summary: PyGAMer: Geometry-preserving Adaptive Mesher
Home-page: https://github.com/ctlee/gamer
Author: The GAMer Team
Author-email: ctlee@ucsd.edu
Maintainer: Christopher T. Lee
Maintainer-email: ctlee@ucsd.edu
License: LGPLv2+
Keywords: meshing
Platform: Windows
Platform: Linux
Platform: Mac OS-X
Platform: Unix
Classifier: Development Status :: 4 - Beta
Classifier: Environment :: Console
Classifier: Intended Audience :: Science/Research
Classifier: License :: OSI Approved :: GNU Lesser General Public License v2 or later (LGPLv2+)
Classifier: Natural Language :: English
Classifier: Operating System :: OS Independent
Classifier: Programming Language :: C++
Classifier: Programming Language :: Python :: 3 :: Only
Classifier: Programming Language :: Python :: Implementation :: CPython
Classifier: Topic :: Scientific/Engineering :: Bio-Informatics
Classifier: Topic :: Scientific/Engineering :: Chemistry
Classifier: Topic :: Scientific/Engineering :: Mathematics
Classifier: Topic :: Scientific/Engineering :: Physics
Classifier: Topic :: Scientific/Engineering :: Visualization
Requires-Dist: numpy (>=1.8.0)
Provides-Extra: docs
Requires-Dist: sphinx ; extra == 'docs'
Requires-Dist: breathe ; extra == 'docs'
Requires-Dist: exhale ; extra == 'docs'
Requires-Dist: sphinx-issues ; extra == 'docs'
Requires-Dist: nbsphinx ; extra == 'docs'
Requires-Dist: jupyter-sphinx ; extra == 'docs'
Requires-Dist: threevis ; extra == 'docs'
Provides-Extra: test
Requires-Dist: pytest ; extra == 'test'
